{"Year":1979,"Author":"Ахмаров Азат","Book":"В августе 79-го, или Back in the USSR","Series":"","Annotation":"Наш современник проваливается во времена Брежнева. Становится суперпопулярным музыкантом и продюсером.","Score":5,"State":"издано","ReviewNumber":"#Н/Д","cc2":"","FromExternal":"","CommentTransfer":"","auth2":"","auth3":"","BookUrl":"https://www.litres.ru/azat-nurgalievich-ahmarov/v-avguste-79-go-ili-back-in-the-ussr/","Nm":222,"Epoch":"","ReviewUrl":"","OriginalYear":1979,"AuthorName":"Азат","Gender":"","SeriesNumber":"","BookId":431,"AuthorEng":"akhmarov_azat","BookEng":"v_avguste_79_go_ili_back_in_the_ussr","SeriesEng":"","StateEnum":"S","BackForth":"","WithBody":"","WithStuff":"","WithGround":"","HasMagic":"","HasSuperSkills":"","FromAge":"","ToAge":"","OnlyMind":"","NumberTransferred":"","PictureUrl":"https://cv3.litres.ru/pub/c/cover_250/43457039.webp","BookSize":"","SameLocation":"","ToCountry":"","ToRegion":"","Review":"","ReviewPictureUrl":"","ReviewBy":""}