{"Year":1100,"Author":"Акулина","Book":"Новый день","Annotation":"Эрика не ждала, что из двадцать первого века когда-нибудь попадёт в двенадцатый, в глухие пески пустыни. И тем более не могла представить, что жизнь свою ей придётся проводить в вечных странствиях и поисках. Удастся ли ей выбраться в свой родной век? Погибнет ли она от рук тех, кто её ненавидит, или будет уничтожена теми, кто успел её полюбить?..","Score":2,"State":"F","ReviewNumber":"167","BookUrl":"https://author.today/work/146057","Nm":2635,"Epoch":"XII век","ReviewUrl":"https://zen.yandex.ru/media/backinussr/novosti-janra-popadancy-v-proshloe-167-6141872fb44bb37b51ee1495","OriginalYear":1100,"AuthorName":"Акулина","BookId":3567,"AuthorEng":"akulina","BookEng":"novy_den","PictureUrl":"https://cm.author.today/content/2021/09/03/28df339fafd34c0db3db6baa495d33aa.jpg?width=265\u0026height=400\u0026rmode=max\u0026format=webp","HasPictureUrl":1,"Tags":"исторический роман, любовная линия, перемещение во времени, приключения, романтика"}