{"Year":1990,"Author":"Ande","Book":"По своим следам","Annotation":"в девяностые -без роялей.","Score":4,"State":"F","ReviewNumber":"148","BookUrl":"https://author.today/work/136086","Nm":92,"ReviewUrl":"https://zen.yandex.ru/media/backinussr/novosti-janra-popadancy-v-proshloe-148-60e2d1e97671f13f01fd27ab","OriginalYear":1990,"AuthorName":"Ande","Gender":"1","BookId":150,"AuthorEng":"ande","BookEng":"po_svoim_sledam","PictureUrl":"https://cm.author.today/content/2021/07/01/be41e65adb9d4c1e9096cb468cd2cce2.jpg?width=265\u0026height=400\u0026rmode=max\u0026format=webp","HasPictureUrl":1}