{"Year":1894,"Author":"Андреев Александр","Book":"1. Главное - воля!","Series":"Мировой пожар","Annotation":"Попаданка в Аликс - невесту императора Николая II. Симбиот. Сама Аликс отвечает за отношения с Николаем, а попаданка гоняет в хвост и гриву всяких министров и занимается крутым прогрессорством.","Score":3,"State":"застой","ReviewNumber":"#Н/Д","cc2":"","FromExternal":"","CommentTransfer":"","auth2":"","auth3":"","BookUrl":"http://samlib.ru/a/andreew_aleksandr_wasilxewich/glawnoe-wolja.shtml","Nm":1630,"Epoch":"","ReviewUrl":"","OriginalYear":1894,"AuthorName":"Александр","Gender":1,"SeriesNumber":1,"BookId":2233,"AuthorEng":"andreev_aleksandr","BookEng":"1_glavnoe_volya_","SeriesEng":"mirovoy_pozhar","StateEnum":"","BackForth":"","WithBody":"","WithStuff":"","WithGround":"","HasMagic":"","HasSuperSkills":"","FromAge":"","ToAge":"","OnlyMind":"","NumberTransferred":"","PictureUrl":"","BookSize":"","SameLocation":"","ToCountry":"","ToRegion":"","Review":"","ReviewPictureUrl":"","ReviewBy":""}