{"Year":1941,"Author":"Антонов Виталий, Новиков Владимир","Book":"Дайте стройбату оружие","Series":"","Annotation":"В результате взрыва на секретном Объекте рота стройбатовцев оказывается в 22 августа 1941 года.","Score":3,"State":"закончено","ReviewNumber":"#Н/Д","cc2":"","FromExternal":"","CommentTransfer":"","auth2":"Новиков Владимир","auth3":"","BookUrl":"https://fb2.top/dayte-stroybatu-orughie-322458","Nm":705,"Epoch":"","ReviewUrl":"","OriginalYear":1941,"AuthorName":"Владимир","Gender":1,"SeriesNumber":"","BookId":1374,"AuthorEng":"antonov_vitaliy_novikov_vladimir","BookEng":"dayte_stroybatu_oruzhie","SeriesEng":"","StateEnum":"F","BackForth":"","WithBody":"","WithStuff":"","WithGround":"","HasMagic":"","HasSuperSkills":"","FromAge":"","ToAge":"","OnlyMind":"","NumberTransferred":"","PictureUrl":"","BookSize":"","SameLocation":"","ToCountry":"","ToRegion":"","Review":"","ReviewPictureUrl":"","ReviewBy":""}