{"Year":1941,"Author":"Барчук Павел","Book":"2. 13-й отдел НКВД","Series":"Чекист","Annotation":"Вместо заслуженной пенсии - 1941 год, 13-й отдел НКВД, борьба с нечистью и ошибка деда, которую надо исправить. Я исправил. Домой вернули, а там... Сухой закон, Советский союз и генсек со знакомым лицом. Но главное - больше нет любимой работы. Где наша не пропадала? Задача номер один - найти бабку -демона и вернуться обратно в 1941.\nЗадача номер два - выжить в битве под Москвой. Задача номер три - вернуть все на свое место.","Score":3,"State":"F","ReviewNumber":"259","BookUrl":"https://author.today/work/223730","OriginalYear":1941,"AuthorName":"Павел","Gender":"1","SeriesNumber":2,"BookId":1335,"AuthorEng":"barchuk_pavel","BookEng":"2_13_y_otdel_nkvd","SeriesEng":"chekist","PictureUrl":"https://cm.author.today/content/2022/09/28/a63df841ecd243568b17313c11734eaf.jpg?width=265\u0026height=400\u0026rmode=max\u0026format=webp","HasPictureUrl":1,"Tags":"альтернативная история, бабкадемон, великая отечественная война, мистика и тайны, назад в ссср, оса, попаданец"}