{"Year":1908,"Author":"Буланов Константин","Book":"1. Предтечи этажерок","Series":"Перкалевый ангел","Annotation":"Первая Мировая Война дала более чем солидный толчок делу развития авиации. И если до ее начала на вооружении всех армий мира находилось менее 1000 аэропланов, то по ее окончании только в одной Англии были списаны и выставлены на продажу более 10000 штук. Что называется, почувствуйте разницу! И если даже в нашей истории Российская империя вступила в войну, имея самые большие авиационные силы, то что же она сможет выставить на шахматную доску мирового противостояния, окажись в прошлом люди, для которых небо являлось смыслом жизни?","Score":3,"State":"закончено","ReviewNumber":"#Н/Д","BookUrl":"http://samlib.ru/b/bulanow_k_n/perkalevyangel1.shtml","Nm":1459,"OriginalYear":1908,"AuthorName":"Константин","Gender":"1","SeriesNumber":1,"BookId":2023,"AuthorEng":"bulanov_konstantin","BookEng":"1_predtechi_etazherok","SeriesEng":"perkalevy_angel","StateEnum":"F"}