{"Year":1941,"Author":"Бушков Александр","Book":"Струна времени. Военные истории","Annotation":"Весной 1944 года командиру разведывательного взвода поручили сопроводить на линию фронта троих странных офицеров. Странным в них было их неестественное спокойствие, даже равнодушие к происходящему, хотя готовились они к заведомо рискованному делу. И лица их были какие-то ухоженные, холеные, совсем не \u0027боевые\u0027. Один из них незадолго до выхода взял гитару и спел песню. С надрывом, с хрипотцой. Разведчику она настолько понравилась, что он записал слова в свой дневник. Много лет спустя, уже в мирной жизни, он снова услышал эту же песню. Это был новый, как сейчас говорят, хит Владимира Высоцкого. В сорок четвертом великому барду было всего шесть лет, и сочинить эту песню тогда он не мог. Значит, те странные офицеры каким-то образом попали в сорок четвертый из будущего...","Score":3,"State":"S","ReviewNumber":"89","BookUrl":"https://www.litres.ru/aleksandr-bushkov/struna-vremeni-voennye-istorii/","Nm":725,"ReviewUrl":"https://zen.yandex.ru/media/backinussr/novosti-janra-popadancy-v-proshloe-89-5f7c0d92952c3b370ee5550c","OriginalYear":1941,"AuthorName":"Александр","Gender":"1","BookId":1387,"AuthorEng":"bushkov_aleksandr","BookEng":"struna_vremeni_voennye_istorii"}