{"Year":-2000,"Author":"Чи Лана","Book":"Цикл. 2. Золотой цветок Кареша","Series":"Золотой цветок Кареша","Annotation":"Когда научная карьера - главное в твоей жизни, глупо просить у волшебного озера красоты, богатства и женского счастья. Да и в принципе верить в \"\"места силы\"\". Но на что только не понадеешься, если многообещающие раскопки принесли лишь груду черепков и одну золотую подвеску! Юлия Владимировна, археолог с мировым именем, загадала желание: найти древний город и разобраться в причинах его исчезновения. Кто же знал, что здешние боги реальны и понимают просьбы слишком буквально!","Score":3,"State":"F","ReviewNumber":"#Н/Д","BookUrl":"https://author.today/work/series/24985","ReviewUrl":"#Н/Д","BookId":6450,"AuthorEng":"chi_lana","BookEng":"cikl_2_zolotoy_cvetok_karesha","SeriesEng":"zolotoy_cvetok_karesha"}