{"Year":1978,"Author":"Дамиров Рафаэль","Book":"04. Курсант: Назад в СССР 4","Series":"Курсант","Annotation":"Казалось, что жизнь наконец, вошла в размереное русло. Но судьбва снова преподносит испытания...","Score":3,"State":"закончено","ReviewNumber":"267","FromExternal":"07.02.23 16:50 ИВМ","BookUrl":"https://author.today/work/224994","Nm":256,"ReviewUrl":"https://dzen.ru/media/backinussr/novosti-janra-popadancy-v-proshloe-267-6342edd161196056a8420f1b","OriginalYear":1978,"AuthorName":"Рафаэль","Gender":1,"SeriesNumber":4,"BookId":443,"AuthorEng":"damirov_rafael","BookEng":"04_kursant_nazad_v_sssr_4","SeriesEng":"kursant","StateEnum":"F"}