{"Year":1922,"Author":"Дашко Дмитрий","Book":"05. Москва","Series":"Мент","Annotation":"Новый город, новое назначение, новые дела в составе сводной «летучей» бригады. И снова нет покоя оперу из будущего, которого перенесло в двадцатые годы прошлого столетия. Их ведь не зря прозвали «ревущими».","Score":4,"State":"F","ReviewNumber":"136","BookUrl":"https://author.today/work/129294","Nm":1284,"ReviewUrl":"https://zen.yandex.ru/media/backinussr/novosti-janra-popadancy-v-proshloe-136-60a61b6bece43e0c8e09954c","OriginalYear":1922,"AuthorName":"Дмитрий","Gender":"1","SeriesNumber":5,"BookId":1790,"AuthorEng":"dashko_dmitriy","BookEng":"05_moskva","SeriesEng":"ment","PictureUrl":"https://cm.author.today/content/2021/05/14/5c436e2734ce4133b67af54bbb2195d8.jpg?width=265\u0026height=400\u0026rmode=max\u0026format=webp","HasPictureUrl":1,"Tags":"альтернативная история, назад в ссср, попаданец в прошлое, попаданцы, спасти ссср"}