{"Year":1917,"Author":"Дорнбург Александр","Book":"1. Борьба на юге","Series":"Рожденные революцией","Annotation":"О ты мой новый Герой! Тебе лишь только верю! Ты открываешь двери и покоряешь сердца! Офицер императорской армии, рыцарь без страха и упрёка, скользит по волнам революционного прошлого и поражает всех врагов силой своего оружия и мощью интеллекта! Читайте все, но помните: \"Это только присказка, сказка будет впереди!\"","Score":3,"State":"закончено","ReviewNumber":"#Н/Д","BookUrl":"https://author.today/work/148734","AuthorName":"Александр","Gender":1,"SeriesNumber":1,"BookId":1901,"AuthorEng":"dornburg_aleksandr","BookEng":"1_borba_na_yuge","SeriesEng":"rozhdennye_revolyuciey","StateEnum":"F"}