{"Year":1971,"Author":"Дронт Николай","Book":"Ещё раз","Series":"","Annotation":"Вселенец в себя молодого.","Score":3,"State":"издано","ReviewNumber":"15","cc2":"","FromExternal":"","CommentTransfer":"","auth2":"","auth3":"","BookUrl":"https://author.today/work/135234","Nm":416,"Epoch":"","ReviewUrl":"https://author.today/post/61555","OriginalYear":1971,"AuthorName":"Николай","Gender":1,"SeriesNumber":"","BookId":738,"AuthorEng":"dront_nikolay","BookEng":"eshchyo_raz","SeriesEng":"","StateEnum":"S","BackForth":"","WithBody":"","WithStuff":"","WithGround":"","HasMagic":"","HasSuperSkills":"","FromAge":"","ToAge":"","OnlyMind":"","NumberTransferred":"","PictureUrl":"","BookSize":"","SameLocation":"","ToCountry":"","ToRegion":"","Review":"","ReviewPictureUrl":"","ReviewBy":""}