{"Year":1967,"Author":"Дроздов Анатолий","Book":"2. Божья коровка-2","Series":"Божья коровка","Annotation":"Он выжил после боя на Даманском. Герой Советского Союза в 19 лет, художник, музыкант, певец... Таким в стране открыты все дороги. Живи и наслаждайся новой жизнью! Но это только кажется. Не все благополучно в СССР в конце 60-х, процессы разложения его уже запущены. Вот и Коровке прилетело... Что делать? Остаться в стороне, спокойно наблюдая, как распадается огромная страна? Ну, ты-то уцелеешь, приспособишься, тем более, что знаешь, как. Возможно ль изменить историю одной песчинке мироздания? Смешно. Но, может, все же попытаться?..","Score":3,"State":"закончено","ReviewNumber":"302","FromExternal":"13.08.23 WV","BookUrl":"https://author.today/work/237962","ReviewUrl":"https://dzen.ru/a/Y9yY3de3w0y_DK4s","OriginalYear":1967,"AuthorName":"Анатолий","Gender":"1","SeriesNumber":2,"BookId":820,"AuthorEng":"drozdov_anatoliy","BookEng":"2_bozhya_korovka_2","SeriesEng":"bozhya_korovka","StateEnum":"F"}