{"Year":1881,"Author":"Ежов Сергей","Book":"2. Kонтуры нового мира","Series":"Пушинка в урагане","Annotation":"Что случается, когда на вершину власти поднимается человек бесконечно преданный Родине, имеющий хорошее образование и вооружённый самым передовым на этот момент философским учением.","Score":3,"State":"закончено","ReviewNumber":"71","BookUrl":"https://litmarket.ru/books/pushinka-v-uragane-kontury-novogo-mira","Nm":1723,"ReviewUrl":"https://zen.yandex.ru/media/backinussr/novosti-janra-popadancy-v-proshloe-71-5f296a8e1c609c3f72cba4f7","OriginalYear":1881,"AuthorName":"Сергей","Gender":1,"SeriesNumber":2,"BookId":2351,"AuthorEng":"ezhov_sergey","BookEng":"2_kontury_novogo_mira","SeriesEng":"pushinka_v_uragane","StateEnum":"F"}