{"Year":1941,"Author":"Ежов Сергей Юрьевич","Book":"Анархист","Series":"","Annotation":"Анон Дикобразов, биолог, специализирующийся на драконах, в результате непонятной флуктуации переносится из 12 октября 3247 в 14 августа 1941 год, в ближний тыл наступающих немецко-фашистских войск.\n Антон желает помочь справедливой борьбе советского народа, но его исторические знания эпохи близки к нулевым - для него это слишком древняя история: к примеру, много ли знает наш современник о взаимоотношениях Мстислава Храброго и Ярослава Мудрого, или о разграблении королевского дворца в Павии, знакового события истории Италии?\n В распоряжении Антона обширная база данных самых высоких научных достижений XXXIII века, но эти сведения практически бесполезны в диком Средневековье.\n Остаётся полагаться на личный инструментарий драконолога да случайные, отрывочные сведения, память былых увлечений, сохранившиеся в архивах собственной памяти.\n Но главное остаётся ценным во все времена: дружба, верность, преданность, сила духа и чистота помыслов.","Score":3,"State":"пишется","ReviewNumber":"310","cc2":"","FromExternal":"13.08.23 WV","CommentTransfer":"","auth2":"","auth3":"","BookUrl":"https://author.today/work/254014","Nm":"","Epoch":"","ReviewUrl":"https://dzen.ru/a/ZAA1O8MJI2TzyU04","OriginalYear":1941,"AuthorName":"Юрьевич","Gender":1,"SeriesNumber":"","BookId":1410,"AuthorEng":"ezhov_sergey_yurevich","BookEng":"anarkhist","SeriesEng":"","StateEnum":"P","BackForth":"","WithBody":"","WithStuff":"","WithGround":"","HasMagic":"","HasSuperSkills":"","FromAge":"","ToAge":"","OnlyMind":"","NumberTransferred":"","PictureUrl":"","BookSize":"","SameLocation":"","ToCountry":"","ToRegion":"","Review":"","ReviewPictureUrl":"","ReviewBy":""}