{"Year":1970,"Author":"Федин Андрей Анатольевич","Book":"Красавчик. Часть 1","Series":"Красавчик","Annotation":"Приехать из РФ 2000-го года в СССР 1970-го?\nПройтись по советской Москве в кроссовках, джинсах и с мобильным телефоном?\nВстретить давно умерших друзей и родственников?\nПознакомиться с кумирами детства?\nРазбогатеть?\nОбрести невероятные способности?\nВлюбиться?\nКакое оно – настоящее чудо? ","Score":3,"State":"F","ReviewNumber":"437","BookUrl":"https://author.today/work/492511","ReviewUrl":"https://dzen.ru/a/aOtciKJ8pC9oQH9j","BookId":6208,"AuthorEng":"fedin_andrey_anatolevich","BookEng":"krasavchik_chast_1","SeriesEng":"krasavchik"}