{"Year":1789,"Author":"Фетцер Эми","Book":"Любовь не знает преград","Annotation":"Дерзкий и бесстрашный пират Дэн Блэкуэлл спасает тонущую девушку - и с первого взгляда осознает, что перед ним - его мечта, ставшая явью. Дэн не знает только одного - того, что прекрасную Тэсс Рэнфри, его пленницу, его драгоценное сокровище, привело на пиратский корабль приключение столь фантастическое, что поверить в него просто невозможно...","Score":3,"State":"издано","ReviewNumber":"#Н/Д","BookUrl":"https://royallib.com/read/fettser_emi/lyubov_ne_znaet_pregrad.html#0","Nm":1993,"OriginalYear":1789,"AuthorName":"Эми","BookId":2705,"AuthorEng":"fetcer_emi","BookEng":"lyubov_ne_znaet_pregrad","StateEnum":"S"}