{"Year":1916,"Author":"Филиппенков Алексей","Book":"Воронка","Series":"","Annotation":"Обратно в молодость и в окопы Первой Мировой Войны","Score":3,"State":"закончено","ReviewNumber":"#Н/Д","cc2":"","FromExternal":"","CommentTransfer":"","auth2":"","auth3":"","BookUrl":"https://www.google.ru/books/edition/%D0%92%D0%BE%D1%80%D0%BE%D0%BD%D0%BA%D0%B0/mELCBAAAQBAJ?hl=ru\u0026gbpv=1\u0026printsec=frontcover","Nm":1395,"Epoch":"","ReviewUrl":"","OriginalYear":1916,"AuthorName":"Алексей","Gender":1,"SeriesNumber":"","BookId":1946,"AuthorEng":"filippenkov_aleksey","BookEng":"voronka","SeriesEng":"","StateEnum":"F","BackForth":"","WithBody":"","WithStuff":"","WithGround":"","HasMagic":"","HasSuperSkills":"","FromAge":"","ToAge":"","OnlyMind":"","NumberTransferred":"","PictureUrl":"","BookSize":"","SameLocation":"","ToCountry":"","ToRegion":"","Review":"","ReviewPictureUrl":"","ReviewBy":""}