{"Year":1755,"Author":"Фомичёв Сергей","Book":"3. Начальник Америки","Series":"Тихоокеанская сага","Annotation":"Попрыгунчика в пространстве и времени (аж 3 главы его гоняли) конкуренты стреножили на Руси времен Елизаветы Петровны.","Score":3,"State":"закончено","ReviewNumber":"#Н/Д","BookUrl":"https://author.today/work/55007","Nm":2053,"OriginalYear":1755,"AuthorName":"Сергей","Gender":1,"SeriesNumber":3,"BookId":2784,"AuthorEng":"fomichyov_sergey","BookEng":"3_nachalnik_ameriki","SeriesEng":"tikhookeanskaya_saga","StateEnum":"F"}