{"Year":1700,"Author":"Горелик Елена","Book":"1. Времена не выбирают","Series":"Немезида","Annotation":"Что если у истории прорежется весьма извращённое чувство юмора? Что если люди, для которых за 8 лет война стала работой, окажутся в точке, изменения в которой могут привести к совершенно непредсказуемым последствиям?\n Роман именно об этом. А также о том, что можно, будучи до мозга костей рациональным солдатом, мыслящим логикой войны, остаться человеком.\n Итак, год одна тысяча семисотый от Рождества Христова. На дворе ноябрь, сырость и шведы... :)","Score":4,"State":"F","ReviewNumber":"340","FromExternal":"13.08.23 WV","BookUrl":"https://author.today/work/260785","ReviewUrl":"https://dzen.ru/a/ZJQQKmZzW1rw2h3O","OriginalYear":1700,"AuthorName":"Елена","Gender":"2","SeriesNumber":1,"BookId":2882,"AuthorEng":"gorelik_elena","BookEng":"1_vremena_ne_vybirayut","SeriesEng":"nemezida","PictureUrl":"https://cm.author.today/content/2023/06/12/c6e222cb184745b2ab02197b18d33bd9.jpg?width=265\u0026height=400\u0026rmode=max\u0026format=webp","HasPictureUrl":1,"Tags":"альтернативная история, боевая фантастика, петр первый, попаданцы, попаданцы во времени, фантастика"}