{"Year":39,"Author":"Грез Регина","Book":"Древний Рим. Честь преторианца","Series":"Виражи Времени","Annotation":"Валентина хотела провести отпуск в Абхазии, но оказалась в Древнем Риме.","Score":3,"State":"закончено","ReviewNumber":"22","cc2":"","FromExternal":"","CommentTransfer":"","auth2":"","auth3":"","BookUrl":"https://litnet.com/ru/book/drevnii-rim-chest-pretorianca-b145875","Nm":2804,"Epoch":"","ReviewUrl":"https://author.today/post/65343","OriginalYear":39,"AuthorName":"Регина","Gender":2,"SeriesNumber":"","BookId":3796,"AuthorEng":"grez_regina","BookEng":"drevniy_rim_chest_pretorianca","SeriesEng":"virazhi_vremeni","StateEnum":"F","BackForth":"","WithBody":"","WithStuff":"","WithGround":"","HasMagic":"","HasSuperSkills":"","FromAge":"","ToAge":"","OnlyMind":"","NumberTransferred":"","PictureUrl":"","BookSize":"","SameLocation":"","ToCountry":"","ToRegion":"","Review":"","ReviewPictureUrl":"","ReviewBy":""}