{"Year":1609,"Author":"Калинин Даниил","Book":"2. Путь чести","Series":"Орел и Ворон","Annotation":"Наши современники все-таки \"провалились\" в прошлое - теперь они уже не сторонние наблюдатели, а полноценные попаданцы. И их ждет первое серьезное испытание - участие в одном из решающих сражений Смутного времени, битва под Калязином! Главная задача героев - просто выжить...\n Между тем колесо истории, как кажется, уже изменило свой ход!","Score":3,"State":"закончено","ReviewNumber":"307","FromExternal":"13.08.23 WV","BookUrl":"https://author.today/work/246149","ReviewUrl":"https://dzen.ru/a/Y_BthYkjDyK0N8JP","OriginalYear":1609,"AuthorName":"Даниил","Gender":1,"SeriesNumber":2,"BookId":3034,"AuthorEng":"kalinin_daniil","BookEng":"2_put_chesti","SeriesEng":"orel_i_voron","StateEnum":"F"}