{"Year":1984,"Author":"Кириллов Александр","Book":"3. Время перемен. Книга 3","Series":"Время перемен","Annotation":"Виктор Калинин служит в армейском спецназе, выполняя приказы командования как на территории России, так и за ее пределами. Всякое могло случиться в этих командировках. Вот и приключилось с главным героем незабываемое летнее путешествие по Африке.","Score":3,"State":"закончено","ReviewNumber":"#Н/Д","cc2":"","FromExternal":"","CommentTransfer":"","auth2":"","auth3":"","BookUrl":"https://www.litres.ru/book/aleksandr-leonidovich-kirillov/vremya-peremen-3-66259194/","Nm":"","Epoch":"","ReviewUrl":"","OriginalYear":"","AuthorName":"Александр","Gender":1,"SeriesNumber":3,"BookId":257,"AuthorEng":"kirillov_aleksandr","BookEng":"3_vremya_peremen_kniga_3","SeriesEng":"vremya_peremen","StateEnum":"F","BackForth":"","WithBody":"","WithStuff":"","WithGround":"","HasMagic":"","HasSuperSkills":"","FromAge":"","ToAge":"","OnlyMind":"","NumberTransferred":"","PictureUrl":"","BookSize":"","SameLocation":"","ToCountry":"","ToRegion":"","Review":"","ReviewPictureUrl":"","ReviewBy":""}