{"Year":1941,"Author":"Кириллов Александр","Book":"1-7 Цикл","Series":"Будем жить по-новому","Annotation":"Сознание нашего современника, военного пенсионера Александра Королева, попадает через временной портал из июля 2020 в июль 1941 года в тело 27-летнего командира стрелковой роты старшего лейтенанта Александра Кольцова, отступающего с бойцами своей роты под ударами немецко-фашистских захватчиков к Москве. Александру ничего не остается, как принять данную реальность, и начать новую жизнь с учетом своего опыта и знаний будущего.","Score":3,"State":"F","ReviewNumber":"90","BookUrl":"https://litnet.com/ru/book/budem-zhit-po-novomu-soprotivlenec-b276513","ReviewUrl":"https://zen.yandex.ru/media/backinussr/novosti-janra-popadancy-v-proshloe-90-5f84066142a69673f7848ec6","BookId":6262,"AuthorEng":"kirillov_aleksandr","BookEng":"1_7_cikl_","SeriesEng":"budem_zhit_po_novomu"}