{"Year":1984,"Author":"Кириллов Александр","Book":"4. Время перемен. Книга 4","Series":"Время перемен","Annotation":"Виктор Калинин, совершив по пути очередные подвиги, возвратился в родную страну. И снова перед ним встал вопрос, какой путь избрать в своей жизни - обычного военного пенсионера или что-то иное, более интересное.","Score":3,"State":"закончено","ReviewNumber":"#Н/Д","BookUrl":"https://www.litres.ru/book/aleksandr-leonidovich-kirillov/vremya-peremen-4-66636946/","AuthorName":"Александр","Gender":1,"SeriesNumber":4,"BookId":258,"AuthorEng":"kirillov_aleksandr","BookEng":"4_vremya_peremen_kniga_4","SeriesEng":"vremya_peremen","StateEnum":"F"}