{"Year":1982,"Author":"Климонов Юрий, Лебедева Наталия Евгеньевна","Book":"6. Новые горизонты","Series":"Мир станет другим","Annotation":"Человечество подходит к апофеозу своего развития, благодаря которому стали возможны самые фантастические проекты. Но зависть - плохое чувство, поэтому зависникам осталось недолго. Даже если они инопланетяне.","Score":3,"State":"F","ReviewNumber":"#Н/Д","BookUrl":"https://author.today/work/series/26670","ReviewUrl":"#Н/Д","BookId":6131,"AuthorEng":"klimonov_yuriy_lebedeva_nataliya_evgenevna","BookEng":"6_novye_gorizonty","SeriesEng":"mir_stanet_drugim"}