{"Year":1935,"Author":"Колмаков Владислав","Book":"2. Шанс для истребителя (Битва за Британию)","Series":"Шанс для истребителя","Annotation":"Александру Матросову приходится бежать из СССР, спасая свою любимую женщину от ареста. Теперь их путь лежит в мир пресловутого Запада. Став невольным изгнанником, советский ас пытается найти убежище в Великобритании. Но за все надо платить. Таков главный закон капитализма. И нашему герою придется отработать входной билет. Ему надо снова повоевать в воздухе. Ведь больше он ничего другого делать не умеет. А Англии сейчас как раз очень требуются услуги профессионального летчика-истребителя. Вторая Мировая война пока еще не затронула Советский Союз. Но она уже вовсю полыхает в Европе. Под ударами гитлеровских орд пали Польша, Голландия, Бельгия, Норвегия и Франция. И теперь настал черед Британии. Немцы настроены решительно. Начинается грандиозная \"Битва за Британию\", которая развернется в воздухе. И беглому русскому асу новые покровители предлагают в ней поучаствовать. С фашистами можно воевать, даже сидя в кабине британского истребителя.","Score":3,"State":"закончено","ReviewNumber":"251","cc2":"","FromExternal":"07.02.23 16:50 ИВМ","CommentTransfer":"","auth2":"","auth3":"","BookUrl":"https://author.today/work/215796","Nm":1076,"Epoch":"","ReviewUrl":"https://zen.yandex.ru/media/backinussr/novosti-janra-popadancy-v-proshloe-251-630997eb565c9b2fdf2b5758?\u0026","OriginalYear":1935,"AuthorName":"Владислав","Gender":1,"SeriesNumber":2,"BookId":1682,"AuthorEng":"kolmakov_vladislav","BookEng":"2_shans_dlya_istrebitelya_bitva_za_britaniyu_","SeriesEng":"shans_dlya_istrebitelya","StateEnum":"F","BackForth":"","WithBody":"","WithStuff":"","WithGround":"","HasMagic":"","HasSuperSkills":"","FromAge":"","ToAge":"","OnlyMind":"","NumberTransferred":"","PictureUrl":"","BookSize":"","SameLocation":"","ToCountry":"","ToRegion":"","Review":"","ReviewPictureUrl":"","ReviewBy":""}