{"Year":1128,"Author":"Красницкий Евгений","Book":"7. Сотник. Не властью единой","Series":"Сотник","Annotation":"1128 г. Турово-Пинское княжество.\nПосле возвращения из Царьграда Михайлу-сотника ожидает новая напасть: по ложному доносу его подозревают в предательстве интересов Мстислава Владимировича, главного князя Руси. Через турово-пинского князя Мише настойчиво предлагают срочно явиться в Киев для объяснений.\nОднако Михайла получает сведения о том, что до Киева его не довезут — убьют куда раньше. И что против его самого и его людей готовится военная провокация с последующим захватом всего Погорынья.\nЕхать нельзя, и не ехать тоже нельзя.\nСотник принимает решение ехать и… не доехать. Он намерен тайно вернуться, найти и обезвредить врагов, обезопасить свою землю и восстановить свое доброе имя.\nОднако враги изворотливы и хитры. Их множество, и за ними — какая-то тайная сила…","Score":3,"State":"S","ReviewNumber":"255","FromExternal":"07.02.23 16:50 ИВМ","BookUrl":"https://www.litres.ru/evgeniy-krasnickiy/sotnik-ne-vlastu-edinoy/","Nm":2616,"ReviewUrl":"https://zen.yandex.ru/media/backinussr/novosti-janra-popadancy-v-proshloe-255-6316dce213d3a151d778ed7c","OriginalYear":1128,"AuthorName":"Евгений","Gender":"1","SeriesNumber":7,"BookId":3546,"AuthorEng":"krasnickiy_evgeniy","BookEng":"7_sotnik_ne_vlastyu_edinoy","SeriesEng":"sotnik"}