{"Year":-1323,"Author":"Курамшина Диана","Book":"1. Чёрная Земля. Подселенка","Series":"Чёрная земля","Annotation":"Иногда случается, что вам делают предложение, от которого невозможно отказаться. Да, в принципе, вашего желания и не спрашивают, отправляя исполнить \"важное\" поручение. И весь вопрос в том, начнёте вы его выполнять с \"душой\"... или...","Score":3,"State":"F","ReviewNumber":"247","FromExternal":"07.02.23 16:50 ИВМ","BookUrl":"https://litmarket.ru/books/chyornaya-zemlya","Nm":3355,"Epoch":"14 век до нашей эры","ReviewUrl":"https://zen.yandex.ru/media/backinussr/novosti-janra-popadancy-v-proshloe-247-62fa1af420f0b73fcb649b0f?\u0026","AuthorName":"Диана","Gender":"2","SeriesNumber":1,"BookId":3900,"AuthorEng":"kuramshina_diana","BookEng":"1_chyornaya_zemlya_podselenka","SeriesEng":"chyornaya_zemlya"}