{"Year":1952,"Author":"Левин Пётр","Book":"Пенсионер А.С. Петров вернулся в СССР, чтобы предупредить тов. Сталина","Annotation":"Умирающий пенсионер загадывает последнее желание: вернуться в СССР. Желание исполнено, но с нюансом: старик оказывается в сибирской глуши в теле кота Васьки. В 1952 году говорящий кот-пенсионер отправляется через всю страну, чтобы спасти Сталина от заговора Берии. Героя ждёт встреча с чекистами, лагерниками и попами. Гротеск, юмор и философия советской души — с котом в главной роли. Такого вы ещё не читали!","Score":3,"State":"F","ReviewNumber":"442","BookUrl":"https://www.litres.ru/book/petr-levin-32634829/pensioner-a-s-petrov-vernulsya-v-sssr-chtoby-predupred-72247063/?source_internal=trial_fragment","ReviewUrl":"https://dzen.ru/a/aQMu8tPcH22is7UH","BookId":6232,"AuthorEng":"levin_pyotr","BookEng":"pensioner_a_s_petrov_vernulsya_v_sssr_chtoby_predupredit_tov_stalina"}