{"Year":1066,"Author":"Логинов Анатолий","Book":"Часть 2. Suum quique. Империя Русь","Series":"Сага о пришельцах из будущего. God, save England!","Annotation":"Рота норфолкских королевских стрелков переносится из 1915 в 1066 год накануне вторжения норманнов в Англию.","Score":3,"State":"застой","ReviewNumber":"#Н/Д","cc2":"","FromExternal":"","CommentTransfer":"","auth2":"","auth3":"","BookUrl":"http://samlib.ru/l/loginow_a_a/saga2.shtml","Nm":2651,"Epoch":"","ReviewUrl":"","OriginalYear":1066,"AuthorName":"Анатолий","Gender":1,"SeriesNumber":"","BookId":3581,"AuthorEng":"loginov_anatoliy","BookEng":"chast_2_suum_quique_imperiya_rus","SeriesEng":"saga_o_prishelcakh_iz_budushchego_god_save_england_","StateEnum":"","BackForth":"","WithBody":"","WithStuff":"","WithGround":"","HasMagic":"","HasSuperSkills":"","FromAge":"","ToAge":"","OnlyMind":"","NumberTransferred":"","PictureUrl":"","BookSize":"","SameLocation":"","ToCountry":"","ToRegion":"","Review":"","ReviewPictureUrl":"","ReviewBy":""}