{"Year":1900,"Author":"Логинов Анатолий","Book":"3. Первый император. Эндшпиль","Series":"Первый император","Annotation":"Третья книга. Пятой в цикле числилась из-за публикаций об армиях и флотах...\nИтак, война о которой так много говорили с 70-х годов девятнадцатого века, началась... и закончилась с неожиданными результатами. ","Score":3,"State":"F","ReviewNumber":"90","FromExternal":"07.02.23 16:50 ИВМ","BookUrl":"https://author.today/work/93745","Nm":3416,"ReviewUrl":"https://zen.yandex.ru/media/backinussr/novosti-janra-popadancy-v-proshloe-90-5f84066142a69673f7848ec6","AuthorName":"Анатолий","Gender":"1","SeriesNumber":3,"BookId":2180,"AuthorEng":"loginov_anatoliy","BookEng":"3_pervy_imperator_endshpil","SeriesEng":"pervy_imperator","PictureUrl":"https://cm.author.today/content/2020/10/12/3fe2e6364f684cb3be564e2111df5f67.jpg?width=265\u0026height=400\u0026rmode=max\u0026format=webp","HasPictureUrl":1}