{"Year":1941,"Author":"Махров Алексей, Злотников Роман","Book":"Дорога к Вождю (4 книги)","Annotation":"Звонок, поступивший на мобильный застрявшего в пробке менеджера среднего звена Виталия Дубинина, не сильно отвлек его от мыслей о грядущем отпуске. Но все изменилось, когда он понял, что на другом конце \u0027провода\u0027 Иосиф Сталин...","Score":3,"State":"издано","ReviewNumber":"#Н/Д","auth2":"Злотников Роман","BookUrl":"http://flibusta.is/s/42261","Nm":883,"OriginalYear":1941,"AuthorName":"Роман","Gender":"1","BookId":1453,"AuthorEng":"makhrov_aleksey_zlotnikov_roman","BookEng":"doroga_k_vozhdyu_4_knigi_","StateEnum":"S"}