{"Year":1992,"Author":"Марченко Геннадий, Alex Pol","Book":"Место под тенью","Annotation":"Он никак не ожидал, что, повздорив с начальником, перенесётся из 2021 года в 1992-й. Вернее, в самого себя, только на 29 лет младше. СССР больше не существует, полным ходом идёт передел собственности, и Сергей Сычин по прозвищу Сыч против своей воли окажется втянут в водоворот событий, от которых хотел бы держаться подальше.\n Но плыть по течению Сыч не собирается. Тем более что от бывшего одноклассника следует весьма заманчивое предложение.","Score":3,"State":"F","ReviewNumber":"157","auth2":"Alex Pol ","BookUrl":"https://author.today/work/143112","Nm":64,"ReviewUrl":"https://zen.yandex.ru/media/backinussr/novosti-janra-popadancy-v-proshloe-157-611b4961b1f1c63a7abffc58","OriginalYear":1992,"BookId":118,"AuthorEng":"marchenko_gennadiy_alex_pol","BookEng":"mesto_pod_tenyu","PictureUrl":"https://cm.author.today/content/2021/08/14/35482ee18429497794194e6e67becfad.jpg?width=265\u0026height=400\u0026rmode=max\u0026format=webp","HasPictureUrl":1,"Tags":"выживание, попаданцы, развитие героя"}