{"Year":1991,"Author":"Мархасин Вадим","Book":"Когда-нибудь мы будем вместе","Annotation":"Я Ельцин панимашь. Президент всея России. Только вот незадача - ничего не помню о своей жизни до декабря девяносто первого года. Ну с кем не бывает, стукнулся где-то головой, понимашь, амнезия и случилась. Напрягает меня другое - то, что я \"помню\" наперед, не произошедшие еще события. И события эти, как президенту, мне категорически не нравятся па-ни-машь! А все вокруг торопят и подгоняют, им все нравится. Штаа делать, как быть?","Score":3,"State":"закончено","ReviewNumber":"7","BookUrl":"http://samlib.ru/m/marhasin_w_m/kogdanibud1-1.shtml","Nm":77,"ReviewUrl":"https://author.today/post/58153","OriginalYear":1991,"AuthorName":"Вадим","Gender":1,"BookId":136,"AuthorEng":"markhasin_vadim","BookEng":"kogda_nibud_my_budem_vmeste","StateEnum":"F"}