{"Year":1942,"Author":"Маркс, и Энгельс","Book":"Операция \"Fredericus\"","Annotation":"Атака Красной Армии началась с попытки стратегического наступления, а завершилась окружением и практически полным уничтожением наступавших советских войск во время «операции Fredericus». Из-за катастрофы стало возможным стремительное продвижение немцев на южном участке фронта на Воронеж и Ростов-на-Дону с последующим выходом к Волге и продвижением на Кавказ.\nПопаданец из 21 века, оказавшийся в на этом участке фронта, решил переломить ход истории...","Score":3,"State":"пишется","ReviewNumber":"362","FromExternal":"14.12.23 WV","BookUrl":"https://author.today/work/306493","ReviewUrl":"https://boosty.to/popal/posts/e42cf393-4938-4702-861e-134ebefb1a87","OriginalYear":1942,"AuthorName":"Энгельс","BookId":1012,"AuthorEng":"marks_i_engels","BookEng":"operaciya_fredericus_","StateEnum":"P"}