{"Year":1953,"Author":"Метельсаев Николай","Book":"Главный инженер завода в СССР","Annotation":"Шел я себе по делам, обычный и простой парень, любитель бухла, курортов и инстадевочек, и вдруг оказываюсь в прошлом, в марте 1953 года, да ещё и инженером-тракторостроителем!\nЗа что???\nВы представляете, какая теперь на мне ответственность???\nА ещё жена, любовница и директор, от которого кровь стынет в печени!\nА ещё кто-то из спецслужб проводит странные эксперименты с моим сознанием, и меня ставят перед сложным выбором - или делать трактора сверх плана, или опыты будут всё более глубокими.","Score":3,"State":"закончено","ReviewNumber":"265","FromExternal":"07.02.23 16:50 ИВМ","Nm":591,"ReviewUrl":"https://dzen.ru/a/Yzpv5QZlVEDzG6bb?\u0026","OriginalYear":1953,"AuthorName":"Николай\n","BookId":953,"AuthorEng":"metelsaev_nikolay","BookEng":"glavny_inzhener_zavoda_v_sssr","StateEnum":"F"}