{"Year":-1500,"Author":"Пономарев Александр","Book":"Основной компонент","Annotation":"Если попал, так попал. И никого не интересует хочешь ты воевать или нет. Копье в руки, барабан на шею, якорную цепь на ногу и поезд на встречу. Таков горький хлеб попаданца.","Score":2,"State":"закончено","ReviewNumber":"133","BookUrl":"https://www.litres.ru/aleksandr-ponomarev-26779878/osnovnoy-komponent-64919066/","Nm":2883,"Epoch":"II—I тыс. до н. э.","ReviewUrl":"https://zen.yandex.ru/media/backinussr/novosti-janra-popadancy-v-proshloe-133-60938abdb8e935293c559949","OriginalYear":-1500,"AuthorName":"Александр","Gender":"1","BookId":3913,"AuthorEng":"ponomarev_aleksandr","BookEng":"osnovnoy_komponent","StateEnum":"F"}