{"Year":1705,"Author":"Посняков Андрей","Book":"2. Капитан-командор","Series":"Пират","Annotation":"На дворе - самое начало восемнадцатого века, война за Испанское наследство, и наш современник, Андрей Громов, ведет своих верных друзей в бой!","Score":3,"State":"F","ReviewNumber":"#Н/Д","BookUrl":"http://flibusta.is/b/348542","Nm":2108,"OriginalYear":1705,"AuthorName":"Андрей","Gender":"1","SeriesNumber":2,"BookId":2870,"AuthorEng":"posnyakov_andrey","BookEng":"2_kapitan_komandor","SeriesEng":"pirat"}