{"Year":1904,"Author":"Протасов Сергей","Book":"6. Перелом","Series":"Цусимские хроники","Annotation":"Превратности войны непредсказуемы. Из малых случайностей, дополняющих одна другую, может вырасти крупная неприятность. И тогда все, к чему уже успели привыкнуть, сметается внезапно и грубо. Вот и во Владивостоке за последние почти полгода прочно уверовали в невозможность полномасштабного вторжения в окрестные воды, но оказались жестоко разочарованы. Последовавшие за этим действия обеих сторон привели к так не желаемому Рожественским очередному генеральному сражению, где удача, которая, как известно, любит подготовленных, опять была на стороне русских. Однако противник показал себя с новой, неожиданной стороны.","Score":3,"State":"издано","ReviewNumber":"289","cc2":"","FromExternal":"07.02.23 16:50 ИВМ","CommentTransfer":"","auth2":"","auth3":"","BookUrl":"https://knizhnik.org/sergej-protasov/perelom","Nm":1538,"Epoch":"","ReviewUrl":"https://dzen.ru/a/Y6ASeQR_W1yvvs9g","OriginalYear":1904,"AuthorName":"Сергей","Gender":1,"SeriesNumber":6,"BookId":2107,"AuthorEng":"protasov_sergey","BookEng":"6_perelom","SeriesEng":"cusimskie_khroniki","StateEnum":"S","BackForth":"","WithBody":"","WithStuff":"","WithGround":"","HasMagic":"","HasSuperSkills":"","FromAge":"","ToAge":"","OnlyMind":"","NumberTransferred":"","PictureUrl":"","BookSize":"","SameLocation":"","ToCountry":"","ToRegion":"","Review":"","ReviewPictureUrl":"","ReviewBy":""}