{"Year":1978,"Author":"Птица Алексей","Book":"2. Сомали: Чёрный пират.","Series":"Мамба в Сомали","Annotation":"Движимый грандиозными планами и поставивший себе великие цели превратить чёрный континент из источника дешёвой раб-силы и ресурсного придатка капитализма в процветающий конгломерат богатых государств, главный герой пускается во все тяжкие. Ведь для достижения поставленных задач все средства хороши! А то, что лес рубят – щепки летят, всем давно известно. .. Да и первый миллион никогда не бывает честным! Баширу Бинго придётся попотеть, выкручиваясь из самых разных передряг.","Score":3,"State":"закончено","ReviewNumber":"293","FromExternal":"07.02.23 16:50 ИВМ","BookUrl":"https://author.today/work/241337\n","Nm":264,"ReviewUrl":"https://dzen.ru/media/backinussr/novosti-janra-popadancy-v-proshloe-293-63bc32c7a899b50db4d3e3b3","OriginalYear":1978,"AuthorName":"Алексей","Gender":1,"SeriesNumber":2,"BookId":452,"AuthorEng":"ptica_aleksey","BookEng":"2_somali_chyorny_pirat_","SeriesEng":"mamba_v_somali","StateEnum":"F"}