{"Year":1915,"Author":"Респов Андрей","Book":"1. Тень Миротворца","Series":"Матрикул","Annotation":"История необычного попаданца. Прожить три жизни: прадеда, деда и свою доведётся не всякому. Мне \"повезло\". Не по собственной воле, а по принуждению сил, пожелавших сделать меня орудием для неведомых целей. Да и бог с ними, если бы на другой чаше весов не лежала жизнь моих близких.\n Так уж случилось, что война не коснулась моей благополучной жизни, но научиться убивать всё же придётся. Иначе не только не выжить – но и не сохранить жизнь родным людям. И умереть придётся не один раз. Лишь бы в этом был толк, и цена не стала слишком неподъёмной. Вот такой из меня Миротворец. Вернее, Тень Миротворца.\n Судьба любит пошутить. Вот только юмор у неё всё больше чёрный.","Score":4,"State":"пишется","ReviewNumber":"330","cc2":"","FromExternal":"13.08.23 WV","CommentTransfer":"","auth2":"","auth3":"","BookUrl":"https://author.today/work/138498","Nm":"","Epoch":"","ReviewUrl":"https://dzen.ru/a/ZGGy1guUKnBUmBHk","OriginalYear":1915,"AuthorName":"Андрей","Gender":1,"SeriesNumber":1,"BookId":1966,"AuthorEng":"respov_andrey","BookEng":"1_ten_mirotvorca","SeriesEng":"matrikul","StateEnum":"P","BackForth":"","WithBody":"","WithStuff":"","WithGround":"","HasMagic":"","HasSuperSkills":"","FromAge":"","ToAge":"","OnlyMind":"","NumberTransferred":"","PictureUrl":"","BookSize":"","SameLocation":"","ToCountry":"","ToRegion":"","Review":"","ReviewPictureUrl":"","ReviewBy":""}