{"Year":1904,"Author":"Романов Герман","Book":"1 -2 «Два доллара»","Series":"Армада","Annotation":"Лето 1898 года - Северо-Американские Соединенные Штаты продемонстрирова-ли всем странам мира, кто является отныне хозяином «Нового Света». Испания как нельзя лучше подошла для «показательной порки», да и повод имелся весомый. Произошел взрыв на броненосном крейсере «Мэн», командир которого получил телеграмму с кодовой фразой","Score":3,"State":"F","BookUrl":"https://author.today/work/series/36651","BookId":5102,"AuthorEng":"romanov_german","BookEng":"1_2_dva_dollara_","SeriesEng":"armada"}