{"Year":1941,"Author":"Романов Герман","Book":"1. Неприступный бастион","Series":"Линия Сталина\u0027","Annotation":"Страшно угодить в кровавое дымное лето 1941 года, попав не на свою войну. Хлебнувший лиха в Карабахе и Чечне, военный пенсионер по инвалидности подполковник в отставке Николай Гловацкий проваливается в прошлое, прямиком под гусеницы победно наступающих на Ленинград немецких танков. Тут надо забыть про \u0027Малой кровью, могучим ударом\u0027, а встать насмерть, отдав приказ \u0027ни шагу назад\u0027. Ведь если остановить фашистов под стенами Пскова, где вросли в землю бетонные коробки дотов \u0027Линии Сталина\u0027, то не умрут от голода миллионы ленинградцев?! Именно здесь родилась в 1918 году Красная Армия, которая и сейчас сможет остановить зарвавшегося врага.","Score":3,"State":"S","ReviewNumber":"#Н/Д","BookUrl":"http://flibusta.is/b/534289","Nm":959,"OriginalYear":1941,"AuthorName":"Герман","Gender":"1","SeriesNumber":1,"BookId":1160,"AuthorEng":"romanov_german","BookEng":"1_nepristupny_bastion","SeriesEng":"liniya_stalina_"}