{"Year":1941,"Author":"Савин Влад","Book":"04. Белая субмарина","Series":"Морской Волк","Annotation":"Атомная подводная лодка \u0027Воронеж\u0027 проваливается из 2012 в 1942 год. Наводит шорох в Северном Ледовитом Океане и не только. Рассправившись с немцами, переключается на бритов и американцев.","Score":2,"State":"издано","ReviewNumber":"#Н/Д","BookUrl":"http://flibusta.is/b/344605","Nm":666,"OriginalYear":1942,"AuthorName":"Влад","Gender":"1","SeriesNumber":4,"BookId":1175,"AuthorEng":"savin_vlad","BookEng":"04_belaya_submarina","SeriesEng":"morskoy_volk","StateEnum":"S"}