{"Year":1918,"Author":"Шалашов Евгений","Book":"12. Ирландские танцы","Series":"Чекист","Annotation":"Приключения товарища Аксенова - Кустова продолжаются ","Score":3,"State":"закончено","ReviewNumber":"358","cc2":"","FromExternal":"19.10.23 WV","CommentTransfer":"","auth2":"","auth3":"","BookUrl":"https://author.today/work/301725","Nm":"","Epoch":"","ReviewUrl":"https://boosty.to/popal/posts/05f80c16-63a7-4246-b311-c0fec501a656","OriginalYear":1918,"AuthorName":"Евгений","Gender":1,"SeriesNumber":12,"BookId":1855,"AuthorEng":"shalashov_evgeniy","BookEng":"12_irlandskie_tancy","SeriesEng":"chekist","StateEnum":"F","BackForth":"","WithBody":"","WithStuff":"","WithGround":"","HasMagic":"","HasSuperSkills":"","FromAge":"","ToAge":"","OnlyMind":"","NumberTransferred":"","PictureUrl":"","BookSize":"","SameLocation":"","ToCountry":"","ToRegion":"","Review":"","ReviewPictureUrl":"","ReviewBy":""}