{"Year":1917,"Author":"Щербаков Алексей","Book":"6. Черт нас рассудит","Series":"Журналисты не отдыхают","Annotation":"Циничный и беспринципный раздолбай-журналист оказывается в апреле 1917 года в Петрограде. Он не собирается спасать Россию . Но журналисты не отдыхают. Остается ввязаться в игру...","Score":3,"State":"застой","ReviewNumber":"#Н/Д","BookUrl":"http://samlib.ru/s/sherbkakow_a_j/chert-1.shtml","Nm":1376,"OriginalYear":1917,"AuthorName":"Алексей","Gender":"1","SeriesNumber":6,"BookId":1876,"AuthorEng":"shcherbakov_aleksey","BookEng":"6_chert_nas_rassudit","SeriesEng":"zhurnalisty_ne_otdykhayut"}