{"Year":1742,"Author":"shellina","Book":"6. Вендетта","Series":"Внук Петра Великого","Annotation":"Петр III стал императором, но более всего он хочет отомстить. Удастся ли ему это?","Score":3,"State":"закончено","ReviewNumber":"308","FromExternal":"13.08.23 WV","BookUrl":"https://author.today/work/245944","ReviewUrl":"https://dzen.ru/a/Y_RlgKSwDHqhLEdn","OriginalYear":1742,"AuthorName":"shellina","Gender":2,"SeriesNumber":6,"BookId":2808,"AuthorEng":"shellina","BookEng":"6_vendetta","SeriesEng":"vnuk_petra_velikogo","StateEnum":"F"}