{"Year":1976,"Author":"Шелест Михаил","Book":"1. Изменить будущее","Series":"Попытка вмешательства","Annotation":"Многие сейчас задумываются, можно ли было не доводить СССР до развала, безболезненно перейти на новые рельсы социалистического, а не капиталлистического хозяйствования. Главный герой книги тоже задумывался над этими вопросами и вдруг вернулся в 1976 год в своё юношеское тело. Новую жизнь главный герой решил прожить так же, как и старую, но попытаться изменить будущее и не допустить развала СССР. Кое что у него получилось.","Score":3,"State":"F","ReviewNumber":"237","FromExternal":"07.02.23 16:50 ИВМ","BookUrl":"https://author.today/work/206636","Nm":346,"ReviewUrl":"https://zen.yandex.ru/media/backinussr/novosti-janra-popadancy-v-proshloe-237-62ce5dc9bd5f802af173a84f?\u0026","OriginalYear":1976,"AuthorName":"Михаил","Gender":"1","SeriesNumber":1,"BookId":579,"AuthorEng":"shelest_mikhail","BookEng":"1_izmenit_budushchee","SeriesEng":"popytka_vmeshatelstva","PictureUrl":"https://cm.author.today/content/2022/07/16/0de1d96d432e46eb9a9d3906fb5e3958.jpg?width=265\u0026height=400\u0026rmode=max\u0026format=webp","HasPictureUrl":1,"Tags":"альтернативная история, 80е, агенты и шпионы, перестройка, попаданцы, спасти ссср, фантастика"}