{"Year":1742,"Author":"shellina","Book":"7. Вендетта. Том 2","Series":"Внук Петра Великого","Annotation":"Последняя, скорее всего, книга про попаданца в Петра III","Score":3,"State":"пишется","ReviewNumber":"345","cc2":"1","FromExternal":"13.08.23 WV","BookUrl":"https://author.today/work/271611","ReviewUrl":"https://dzen.ru/a/ZLTCQc1mam-xadjY","OriginalYear":1742,"AuthorName":"shellina","Gender":"2","SeriesNumber":7,"BookId":2809,"AuthorEng":"shellina","BookEng":"7_vendetta_tom_2","SeriesEng":"vnuk_petra_velikogo","StateEnum":"P"}