{"Year":1825,"Author":"Шерр Михаил","Book":"2. Олигарх 2","Series":"Олигарх","Annotation":"Простой питерский мужик, но очень большой любитель истории, особенно родного Севастополя, оказывается в 19-ом веке молодым русским князем и хочет избежать позора России в Крымской войне. ","Score":3,"State":"F","ReviewNumber":"358","FromExternal":"19.10.23 WV","BookUrl":"https://author.today/work/292576","ReviewUrl":"https://boosty.to/popal/posts/05f80c16-63a7-4246-b311-c0fec501a656","OriginalYear":1825,"AuthorName":"Михаил","Gender":"1","SeriesNumber":2,"BookId":2573,"AuthorEng":"sherr_mikhail","BookEng":"2_oligarkh_2","SeriesEng":"oligarkh","PictureUrl":"https://cm.author.today/content/2023/10/12/85f1b098b7b04dabbc665946bc3988f9.jpg?width=265\u0026height=400\u0026rmode=max\u0026format=webp","HasPictureUrl":1}