{"Year":1801,"Author":"Шопперт Андрей","Book":"4. Кавказ подо мною","Series":"Красавчик","Annotation":"Князя Петра Христиановича фон Витгенштейна -Дербентского вновь отправляют на Кавказ.\n Там столько всего вкусного.","Score":3,"State":"закончено","ReviewNumber":"317","cc2":"","FromExternal":"13.08.23 WV","CommentTransfer":"","auth2":"","auth3":"","BookUrl":"https://author.today/work/258688","Nm":"","Epoch":"","ReviewUrl":"https://dzen.ru/a/ZCUhhWBRtjTDIv2D","OriginalYear":1801,"AuthorName":"Андрей","Gender":1,"SeriesNumber":4,"BookId":2656,"AuthorEng":"shoppert_andrey","BookEng":"4_kavkaz_podo_mnoyu","SeriesEng":"krasavchik","StateEnum":"F","BackForth":"","WithBody":"","WithStuff":"","WithGround":"","HasMagic":"","HasSuperSkills":"","FromAge":"","ToAge":"","OnlyMind":"","NumberTransferred":"","PictureUrl":"","BookSize":"","SameLocation":"","ToCountry":"","ToRegion":"","Review":"","ReviewPictureUrl":"","ReviewBy":""}