{"Year":1947,"Author":"Шопперт Андрей","Book":"3. Вовка-центровой-3","Series":"Вовка-центровой","Annotation":"Закончилась зима, а с ней и хоккейный сезон. Впереди лето, а значит - футбол. Вот только Главный тренер футбольной команды «Динамо» (Москва) Михаил Иосифович Якушин, также известный в футбольных кругах, как «Хитрый Михей», не хочет брать Владимира Фомина в основную команду. Да и в дубль не хочет. На дворе 1948 год и Фомину недавно исполнилось шестнадцать лет.","Score":3,"State":"закончено","ReviewNumber":"224","FromExternal":"07.02.23 16:50 ИВМ","BookUrl":"https://author.today/work/193374","Nm":626,"ReviewUrl":"https://zen.yandex.ru/media/backinussr/novosti-janra-popadancy-v-proshloe-224-6288870321407a6901880094?\u0026","OriginalYear":1947,"AuthorName":"Андрей","Gender":"1","SeriesNumber":3,"BookId":992,"AuthorEng":"shoppert_andrey","BookEng":"3_vovka_centrovoy_3","SeriesEng":"vovka_centrovoy","StateEnum":"F"}