{"Year":1887,"Author":"Соловей Дмитрий","Book":"3. Не вернёмся, не свернём","Series":"Свои - чужие","Annotation":"Главный герой, поддавшись на уговоры друга, покупает дом в старой части Краснодара. По закону жанра попаданства он открывает временной портал в 1887 год. До Октябрьской революции еще тридцать лет. Есть время что-то поменять и изменить в истории страны.","Score":3,"State":"F","ReviewNumber":"69","BookUrl":"https://author.today/work/83814","Nm":1696,"ReviewUrl":"https://zen.yandex.ru/media/backinussr/novosti-janra-popadancy-v-proshloe-69-5f22a4879669f47c3e4d0e5d","OriginalYear":1887,"AuthorName":"Дмитрий","Gender":"1","SeriesNumber":3,"BookId":2310,"AuthorEng":"solovey_dmitriy","BookEng":"3_ne_vernyomsya_ne_svernyom","SeriesEng":"svoi_chuzhie","PictureUrl":"https://cm.author.today/content/2020/07/27/ed7dade17fb74e8cab21040e9b9701d0.jpg?width=265\u0026height=400\u0026rmode=max\u0026format=webp","HasPictureUrl":1,"Tags":"альтернативная реальность, попаданцы"}