{"Year":1756,"Author":"Тюрина Елена","Book":"Тайна оленьего парка","Annotation":"Спас её от надругательства и гибели, а после исчез. Но вскоре снова неожиданно возник в её жизни. Загадочный незнакомец гораздо старше неё, кто он на самом деле? Какую драму скрывает его прошлое? Попав во Францию XVIII века, Катя сразу оказалась замешана в тёмную историю. Теперь главное выжить. А это значит — распутать клубок тайн, что оплели одно элитное учебное заведение, и найти тропинку к израненному сердцу любимого мужчины.","Score":2,"State":"издано","ReviewNumber":"208","FromExternal":"07.02.23 16:50 ИВМ","BookUrl":"https://www.litres.ru/elena-turina/tayny-olenego-parka/chitat-onlayn/","Nm":2049,"ReviewUrl":"https://zen.yandex.ru/media/backinussr/novosti-janra-popadancy-v-proshloe-208-62301973389ab425f3982c94","OriginalYear":1756,"AuthorName":"Елена\n","BookId":2778,"AuthorEng":"tyurina_elena","BookEng":"tayna_olenego_parka","StateEnum":"S"}