{"Year":1888,"Author":"Валериев Игорь","Book":"04. Поход","Series":"Ермак","Annotation":"Сознание матёрого офицера-спецназовца с позывным \u0027Ермак\u0027 переносится в 1888 год в тело четырнадцатилетнего подростка сироты - будущего казака Амурского казачьего войска. Найдёт ли Ермак своё место в новом мире? И если да, то, как это повлияет на действительность, в которой он оказался?","Score":3,"State":"S","ReviewNumber":"16","BookUrl":"https://author.today/work/51455","Nm":1687,"ReviewUrl":"https://author.today/post/61836","OriginalYear":1888,"AuthorName":"Игорь","Gender":"1","SeriesNumber":4,"BookId":2296,"AuthorEng":"valeriev_igor","BookEng":"04_pokhod","SeriesEng":"ermak","PictureUrl":"https://cm.author.today/content/2020/08/07/0b29dc59a70a4a2f929016b3f07087a8.jpg?width=265\u0026height=400\u0026rmode=max\u0026format=webp","HasPictureUrl":1,"Tags":"альтернативная реальность, валериев, ермак, попаданцы"}