{"Year":1754,"Author":"Васильев Николай","Book":"1. Прогрессор галантного века","Series":"Прогрессор галантного века","Annotation":"Студент четвертого курса Сашка Крылов упал с крыши и прямиком в койку книгини Бестужевой.","Score":3,"State":"закончено","ReviewNumber":"#Н/Д","BookUrl":"http://samlib.ru/w/wasilxew_n_f/progressorgalantnogoveka-5.shtml","Nm":2054,"OriginalYear":1754,"AuthorName":"Николай","Gender":"1","SeriesNumber":1,"BookId":2786,"AuthorEng":"vasilev_nikolay","BookEng":"1_progressor_galantnogo_veka","SeriesEng":"progressor_galantnogo_veka","StateEnum":"F"}