{"Year":978,"Author":"Веденин Анатолий","Book":"Время выбора","Series":"","Annotation":"Сознание нашего современника, пожилого ученого - историка сливается с сознанием юного князя Владимира Святославича. Что можно сделать для того, что бы Русь стала единым государством, устремленным в будущее и помнящем прошлое?","Score":3,"State":"закончено","ReviewNumber":"#Н/Д","cc2":"","FromExternal":"","CommentTransfer":"","auth2":"","auth3":"","BookUrl":"http://samlib.ru/w/wedenin_a/vrema.shtml","Nm":2680,"Epoch":"","ReviewUrl":"","OriginalYear":978,"AuthorName":"Анатолий","Gender":1,"SeriesNumber":"","BookId":3618,"AuthorEng":"vedenin_anatoliy","BookEng":"vremya_vybora","SeriesEng":"","StateEnum":"F","BackForth":"","WithBody":"","WithStuff":"","WithGround":"","HasMagic":"","HasSuperSkills":"","FromAge":"","ToAge":"","OnlyMind":"","NumberTransferred":"","PictureUrl":"","BookSize":"","SameLocation":"","ToCountry":"","ToRegion":"","Review":"","ReviewPictureUrl":"","ReviewBy":""}