{"Year":1967,"Author":"Вязовский Алексей","Book":"1. Группа крови на рукаве","Series":"Группа крови на рукаве","Annotation":"Я ехал в Московском метро когда все случилось. Завыли сирены и поезд встал, будто наступил апокалипсис. Поток людей унес меня в черный тоннель. Но выбрался я один и очутился…\nЭто что за тропическая многоножка?! И какого хрена меня долбанули прикладом и связали? Кто они мать такие? Вооруженные головорезы в допотопной зеленой форме пехоты США.\nА это что? Джунгли?.. \nВьетнамская война глазами нашего современника.","Score":4,"State":"закончено","ReviewNumber":"244","cc2":"","FromExternal":"07.02.23 16:50 ИВМ","CommentTransfer":"","auth2":"Дамиров Рафаэль","auth3":"","BookUrl":"https://author.today/work/210575","Nm":491,"Epoch":"","ReviewUrl":"https://zen.yandex.ru/media/backinussr/novosti-janra-popadancy-v-proshloe-244-62ec92b88d94605394003e07","OriginalYear":1967,"AuthorName":"Алексей","Gender":1,"SeriesNumber":1,"BookId":822,"AuthorEng":"vyazovskiy_aleksey","BookEng":"1_gruppa_krovi_na_rukave","SeriesEng":"gruppa_krovi_na_rukave","StateEnum":"F","BackForth":"","WithBody":"","WithStuff":"","WithGround":"","HasMagic":"","HasSuperSkills":"","FromAge":"","ToAge":"","OnlyMind":"","NumberTransferred":"","PictureUrl":"","BookSize":"","SameLocation":"","ToCountry":"","ToRegion":"","Review":"","ReviewPictureUrl":"","ReviewBy":""}