{"Year":450,"Author":"Заозерский Андрей","Book":"Гунны","Annotation":"Задумав отыскать сокровища гуннского правителя Аттилы, владелец музыкального магазина Аркадий Иванов отправляется в Венгрию. Поиски клада приводят его в далекое прошлое — в пятый век.\n Аттила умер, но его последователи и враги упорно дерутся за власть, а черные жрецы собираются принести в жертву своим жестоким богам красавицу из 1956 года — девушку с жемчужными волосами, в которую влюбляется наш герой.\n Для того чтобы спасти возлюбленную, Аркадию предстоит многое пройти — и в современности, и в пятом веке, и в 1956 году, во время знаменитого антисоветского восстания в Венгрии.","Score":3,"State":"закончено","ReviewNumber":"338","FromExternal":"13.08.23 WV","BookUrl":"https://knizhnik.org/andrej-zaozerskij/gunny","Epoch":"5 век","ReviewUrl":"https://dzen.ru/a/ZIqg2qaW3kIxmLf5","OriginalYear":450,"AuthorName":"Андрей","Gender":1,"BookId":3764,"AuthorEng":"zaozerskiy_andrey","BookEng":"gunny","StateEnum":"F"}