{"Year":1988,"Author":"Здрав  Олег","Book":"3. Студент на дембель","Series":"Дембель неизбежен","Annotation":"Два раза срочную? Так не бывает! Но иногда случается. Зато дембель тоже второй раз, если повезет","Score":4,"State":"S","ReviewNumber":"#Н/Д","BookUrl":"https://author.today/work/23857","Nm":115,"OriginalYear":1988,"AuthorName":"Олег","Gender":"1","SeriesNumber":3,"BookId":179,"AuthorEng":"zdrav_oleg","BookEng":"3_student_na_dembel","SeriesEng":"dembel_neizbezhen","PictureUrl":"https://cm.author.today/content/2019/01/16/5ab1ea3a5d234a5bac5b3d053ce8cfa2.png?width=265\u0026height=400\u0026rmode=max\u0026format=webp","HasPictureUrl":1}