{"Year":1979,"Author":"Злотников Роман","Book":"4. Каждому по делам его","Series":"Настоящее прошлое","Annotation":"Роман Марков уже изрядно \"оттоптался на бабочках\", и это начинает приносить \"ягодки\". Да такие, что впору в ступор впадать... Потому что этот не тот мир, который он помнил. Это совершенно новый мир, в котором каждому воздастся по делам его.","Score":3,"State":"P","ReviewNumber":"315","FromExternal":"13.08.23 WV","BookUrl":"https://author.today/work/250448","ReviewUrl":"https://dzen.ru/a/ZBvXReeSfwLBHfKq","OriginalYear":1979,"AuthorName":"Роман","Gender":"1","SeriesNumber":4,"BookId":422,"AuthorEng":"zlotnikov_roman","BookEng":"4_kazhdomu_po_delam_ego","SeriesEng":"nastoyashchee_proshloe","PictureUrl":"https://cm.author.today/content/2023/02/03/a784984dcf54413bbb1b90bf53049546.jpg?width=265\u0026height=400\u0026rmode=max\u0026format=webp","HasPictureUrl":1,"Tags":"альтернативная история, боевик, возвращение в прошлое, история любви, фантастика"}